visualise_spacy_tree/__init__.py
visualise_spacy_tree/visualise_spacy_tree.py
visualise_spacy_tree/test/__init__.py
visualise_spacy_tree/test/test_plot.py
visualise_spacy_tree-0.0.6.dist-info/LICENSE
visualise_spacy_tree-0.0.6.dist-info/METADATA
visualise_spacy_tree-0.0.6.dist-info/WHEEL
visualise_spacy_tree-0.0.6.dist-info/top_level.txt
visualise_spacy_tree-0.0.6.dist-info/RECORD
