Metadata-Version: 2.1
Name: visualise-spacy-tree
Version: 0.0.6
Summary: Create dependency tree plots from SpaCy Doc objects
Home-page: https://github.com/cyclecycle/visualise-spacy-tree
Author: Nicholas Morley
Author-email: nick.morley111@gmail.com
License: UNKNOWN
Platform: UNKNOWN
Classifier: Programming Language :: Python :: 3
Classifier: License :: OSI Approved :: MIT License
Classifier: Operating System :: OS Independent
Requires-Dist: pydot (==1.4.1)
